README.md
setup.py
savnet/__init__.py
savnet/analysis_network.py
savnet/logger.py
savnet/network.py
savnet/parser.py
savnet/preprocess.py
savnet/run.py
savnet/sample_conf.py
savnet/sav.py
savnet/utils.py
savnet/version.py
savnet.egg-info/PKG-INFO
savnet.egg-info/SOURCES.txt
savnet.egg-info/dependency_links.txt
savnet.egg-info/entry_points.txt
savnet.egg-info/requires.txt
savnet.egg-info/top_level.txt