Metadata-Version: 1.1
Name: savnet
Version: 0.3.3
Summary: Python tools for detecting mutations causing splicing changes
Home-page: https://github.com/friend1ws/SAVNet
Author: Yuichi Shiraishi
Author-email: friend1ws@gamil.com
License: GPLv3
Platform: UNKNOWN
Classifier: Development Status :: 4 - Beta
Classifier: Intended Audience :: Science/Research
Classifier: License :: OSI Approved :: GNU General Public License v3 (GPLv3)
Classifier: Operating System :: Unix
Classifier: Programming Language :: Python :: 2.7
Classifier: Topic :: Scientific/Engineering :: Bio-Informatics
